{
  "user": [
    {
      "id": 1,
      "username": "spaceman",
      "password": "password"
    }
  ],
  "items": [
    {
      "quantity": "3",
      "name": "dog treats",
      "aisle": "33",
      "id": 1,
      "archived": false
    },
    {
      "quantity": "2",
      "name": "Cat Treats",
      "aisle": "3333",
      "archived": false,
      "id": 4
    },
    {
      "quantity": "3",
      "name": "updogs",
      "aisle": "2",
      "archived": false,
      "id": 6
    },
    {
      "quantity": "5",
      "name": "Strawberry Jam",
      "aisle": "15",
      "archived": false,
      "id": 7
    },
    {
      "quantity": "200",
      "name": "chocolates",
      "aisle": "2",
      "archived": false,
      "id": 8
    },
    {
      "quantity": "2",
      "name": "asdfsda",
      "aisle": "8",
      "archived": false,
      "id": 9
    }
  ]
}